.gitignore
AUTHORS
CHANGELOG
FAQ
INSTALL
LICENSE
README
TODO
setup.py
wsgiapptools/README
wsgiapptools/__init__.py
wsgiapptools/cookies.py
wsgiapptools/flash.py
wsgiapptools.egg-info/PKG-INFO
wsgiapptools.egg-info/SOURCES.txt
wsgiapptools.egg-info/dependency_links.txt
wsgiapptools.egg-info/entry_points.txt
wsgiapptools.egg-info/not-zip-safe
wsgiapptools.egg-info/top_level.txt
wsgiapptools/templates/css/flash.css
wsgiapptools/templates/mako/flash_messages.html